{
    "imageCoordinateAxisAlignedBBox": [
        [
            1586,
            2001
        ],
        [
            1728,
            2664
        ]
    ],
    "mapCoordinateAxisAlignedBBox": [
        [
            -21.400999999999982,
            -19.405
        ],
        [
            11.749000000000024,
            -26.504999999999995
        ]
    ],
    "walls": [
        {
            "closed": true,
            "beginning": [
                -20.601,
                -20.254999999999995
            ],
            "clockwise": false,
            "center": [
                -4.700999999999993,
                -22.954999999999984
            ],
            "midpoints": [
                [
                    -20.200999999999993,
                    -20.054999999999993
                ],
                [
                    -20.251000000000005,
                    -20.10499999999999
                ],
                [
                    -20.301000000000002,
                    -20.10499999999999
                ],
                [
                    -20.351,
                    -20.154999999999987
                ],
                [
                    -20.400999999999996,
                    -20.154999999999987
                ],
                [
                    -20.450999999999993,
                    -20.204999999999984
                ],
                [
                    -20.501000000000005,
                    -20.204999999999984
                ],
                [
                    -20.551000000000002,
                    -20.254999999999995
                ],
                [
                    -20.601,
                    -20.254999999999995
                ],
                [
                    -20.650999999999996,
                    -20.304999999999993
                ],
                [
                    -20.650999999999996,
                    -20.954999999999984
                ],
                [
                    -20.700999999999993,
                    -21.004999999999995
                ],
                [
                    -20.700999999999993,
                    -21.704999999999984
                ],
                [
                    -20.751000000000005,
                    -21.754999999999995
                ],
                [
                    -20.751000000000005,
                    -22.454999999999984
                ],
                [
                    -20.700999999999993,
                    -22.504999999999995
                ],
                [
                    -20.700999999999993,
                    -22.60499999999999
                ],
                [
                    -20.551000000000002,
                    -22.754999999999995
                ],
                [
                    -20.501000000000005,
                    -22.754999999999995
                ],
                [
                    -20.450999999999993,
                    -22.804999999999993
                ],
                [
                    -20.251000000000005,
                    -22.804999999999993
                ],
                [
                    -20.200999999999993,
                    -22.85499999999999
                ],
                [
                    -19.650999999999996,
                    -22.85499999999999
                ],
                [
                    -19.601,
                    -22.904999999999987
                ],
                [
                    -18.851,
                    -22.904999999999987
                ],
                [
                    -18.801000000000002,
                    -22.85499999999999
                ],
                [
                    -18.650999999999996,
                    -22.85499999999999
                ],
                [
                    -18.601,
                    -22.804999999999993
                ],
                [
                    -18.501000000000005,
                    -22.804999999999993
                ],
                [
                    -18.450999999999993,
                    -22.85499999999999
                ],
                [
                    -18.301000000000002,
                    -22.85499999999999
                ],
                [
                    -18.200999999999993,
                    -22.954999999999984
                ],
                [
                    -17.950999999999993,
                    -22.954999999999984
                ],
                [
                    -17.900999999999996,
                    -23.004999999999995
                ],
                [
                    -17.650999999999996,
                    -23.004999999999995
                ],
                [
                    -17.601,
                    -23.054999999999993
                ],
                [
                    -16.950999999999993,
                    -23.054999999999993
                ],
                [
                    -16.900999999999996,
                    -23.10499999999999
                ],
                [
                    -16.700999999999993,
                    -23.10499999999999
                ],
                [
                    -16.650999999999996,
                    -23.054999999999993
                ],
                [
                    -16.551000000000002,
                    -23.054999999999993
                ],
                [
                    -16.501000000000005,
                    -23.10499999999999
                ],
                [
                    -16.351,
                    -23.10499999999999
                ],
                [
                    -16.251000000000005,
                    -23.204999999999984
                ],
                [
                    -16.200999999999993,
                    -23.204999999999984
                ],
                [
                    -16.101,
                    -23.304999999999993
                ],
                [
                    -16.101,
                    -23.35499999999999
                ],
                [
                    -15.850999999999999,
                    -23.60499999999999
                ],
                [
                    -15.801000000000002,
                    -23.60499999999999
                ],
                [
                    -15.751000000000005,
                    -23.654999999999987
                ],
                [
                    -15.700999999999993,
                    -23.654999999999987
                ],
                [
                    -15.650999999999996,
                    -23.704999999999984
                ],
                [
                    -15.600999999999999,
                    -23.704999999999984
                ],
                [
                    -15.551000000000002,
                    -23.754999999999995
                ],
                [
                    -15.350999999999999,
                    -23.754999999999995
                ],
                [
                    -15.301000000000002,
                    -23.804999999999993
                ],
                [
                    -14.751000000000005,
                    -23.804999999999993
                ],
                [
                    -14.700999999999993,
                    -23.85499999999999
                ],
                [
                    -13.950999999999993,
                    -23.85499999999999
                ],
                [
                    -13.900999999999996,
                    -23.904999999999987
                ],
                [
                    -13.850999999999999,
                    -23.904999999999987
                ],
                [
                    -13.801000000000002,
                    -23.85499999999999
                ],
                [
                    -13.251000000000005,
                    -23.85499999999999
                ],
                [
                    -13.200999999999993,
                    -23.804999999999993
                ],
                [
                    -13.051000000000002,
                    -23.804999999999993
                ],
                [
                    -13.001000000000005,
                    -23.754999999999995
                ],
                [
                    -12.600999999999999,
                    -23.754999999999995
                ],
                [
                    -12.551000000000002,
                    -23.804999999999993
                ],
                [
                    -12.100999999999999,
                    -23.804999999999993
                ],
                [
                    -12.051000000000002,
                    -23.85499999999999
                ],
                [
                    -11.801000000000002,
                    -23.85499999999999
                ],
                [
                    -11.751000000000005,
                    -23.904999999999987
                ],
                [
                    -11.350999999999999,
                    -23.904999999999987
                ],
                [
                    -11.301000000000002,
                    -23.954999999999984
                ],
                [
                    -10.801000000000002,
                    -23.954999999999984
                ],
                [
                    -10.751000000000005,
                    -24.004999999999995
                ],
                [
                    -10.400999999999996,
                    -24.004999999999995
                ],
                [
                    -10.350999999999999,
                    -24.054999999999993
                ],
                [
                    -10.150999999999996,
                    -24.054999999999993
                ],
                [
                    -10.100999999999999,
                    -24.10499999999999
                ],
                [
                    -9.751000000000005,
                    -24.10499999999999
                ],
                [
                    -9.700999999999993,
                    -24.154999999999987
                ],
                [
                    -9.600999999999999,
                    -24.154999999999987
                ],
                [
                    -9.551000000000002,
                    -24.10499999999999
                ],
                [
                    -9.450999999999993,
                    -24.10499999999999
                ],
                [
                    -9.400999999999996,
                    -24.154999999999987
                ],
                [
                    -9.001000000000005,
                    -24.154999999999987
                ],
                [
                    -8.950999999999993,
                    -24.10499999999999
                ],
                [
                    -8.850999999999999,
                    -24.10499999999999
                ],
                [
                    -8.801000000000002,
                    -24.154999999999987
                ],
                [
                    -8.650999999999996,
                    -24.154999999999987
                ],
                [
                    -8.600999999999999,
                    -24.204999999999984
                ],
                [
                    -8.150999999999996,
                    -24.204999999999984
                ],
                [
                    -8.100999999999999,
                    -24.254999999999995
                ],
                [
                    -7.650999999999996,
                    -24.254999999999995
                ],
                [
                    -7.600999999999999,
                    -24.204999999999984
                ],
                [
                    -7.501000000000005,
                    -24.204999999999984
                ],
                [
                    -7.450999999999993,
                    -24.254999999999995
                ],
                [
                    -7.100999999999999,
                    -24.254999999999995
                ],
                [
                    -7.051000000000002,
                    -24.304999999999993
                ],
                [
                    -6.650999999999996,
                    -24.304999999999993
                ],
                [
                    -6.600999999999999,
                    -24.35499999999999
                ],
                [
                    -5.900999999999996,
                    -24.35499999999999
                ],
                [
                    -5.850999999999999,
                    -24.304999999999993
                ],
                [
                    -5.751000000000005,
                    -24.304999999999993
                ],
                [
                    -5.700999999999993,
                    -24.35499999999999
                ],
                [
                    -5.551000000000002,
                    -24.35499999999999
                ],
                [
                    -5.501000000000005,
                    -24.404999999999987
                ],
                [
                    -5.051000000000002,
                    -24.404999999999987
                ],
                [
                    -5.001000000000005,
                    -24.454999999999984
                ],
                [
                    -4.700999999999993,
                    -24.454999999999984
                ],
                [
                    -4.650999999999996,
                    -24.404999999999987
                ],
                [
                    -4.551000000000002,
                    -24.404999999999987
                ],
                [
                    -4.501000000000005,
                    -24.454999999999984
                ],
                [
                    -4.350999999999999,
                    -24.454999999999984
                ],
                [
                    -4.301000000000002,
                    -24.504999999999995
                ],
                [
                    -3.350999999999999,
                    -24.504999999999995
                ],
                [
                    -3.301000000000002,
                    -24.454999999999984
                ],
                [
                    -3.2009999999999934,
                    -24.454999999999984
                ],
                [
                    -3.1509999999999962,
                    -24.504999999999995
                ],
                [
                    -3.0010000000000048,
                    -24.504999999999995
                ],
                [
                    -2.9509999999999934,
                    -24.554999999999993
                ],
                [
                    -2.551000000000002,
                    -24.554999999999993
                ],
                [
                    -2.5010000000000048,
                    -24.60499999999999
                ],
                [
                    -2.100999999999999,
                    -24.60499999999999
                ],
                [
                    -2.051000000000002,
                    -24.554999999999993
                ],
                [
                    -1.9009999999999962,
                    -24.554999999999993
                ],
                [
                    -1.850999999999999,
                    -24.60499999999999
                ],
                [
                    -1.7009999999999934,
                    -24.60499999999999
                ],
                [
                    -1.6509999999999962,
                    -24.654999999999987
                ],
                [
                    -1.2510000000000048,
                    -24.654999999999987
                ],
                [
                    -1.2009999999999934,
                    -24.704999999999984
                ],
                [
                    -0.7009999999999934,
                    -24.704999999999984
                ],
                [
                    -0.6509999999999962,
                    -24.654999999999987
                ],
                [
                    -0.5510000000000019,
                    -24.654999999999987
                ],
                [
                    -0.5010000000000048,
                    -24.704999999999984
                ],
                [
                    -0.3509999999999991,
                    -24.704999999999984
                ],
                [
                    -0.30100000000000193,
                    -24.754999999999995
                ],
                [
                    0.1490000000000009,
                    -24.754999999999995
                ],
                [
                    0.19899999999999807,
                    -24.804999999999993
                ],
                [
                    0.8490000000000038,
                    -24.804999999999993
                ],
                [
                    0.8990000000000009,
                    -24.85499999999999
                ],
                [
                    1.649000000000001,
                    -24.85499999999999
                ],
                [
                    1.698999999999998,
                    -24.904999999999987
                ],
                [
                    2.698999999999998,
                    -24.904999999999987
                ],
                [
                    2.7489999999999952,
                    -24.954999999999984
                ],
                [
                    3.5490000000000066,
                    -24.954999999999984
                ],
                [
                    3.5990000000000038,
                    -24.904999999999987
                ],
                [
                    3.698999999999998,
                    -24.904999999999987
                ],
                [
                    3.7489999999999952,
                    -24.954999999999984
                ],
                [
                    3.899000000000001,
                    -24.954999999999984
                ],
                [
                    3.948999999999998,
                    -25.004999999999995
                ],
                [
                    4.349000000000004,
                    -25.004999999999995
                ],
                [
                    4.399000000000001,
                    -25.054999999999993
                ],
                [
                    4.899000000000001,
                    -25.054999999999993
                ],
                [
                    4.948999999999998,
                    -25.004999999999995
                ],
                [
                    5.049000000000007,
                    -25.004999999999995
                ],
                [
                    5.099000000000004,
                    -25.054999999999993
                ],
                [
                    5.248999999999995,
                    -25.054999999999993
                ],
                [
                    5.299000000000007,
                    -25.10499999999999
                ],
                [
                    5.748999999999995,
                    -25.10499999999999
                ],
                [
                    5.799000000000007,
                    -25.154999999999987
                ],
                [
                    5.948999999999998,
                    -25.154999999999987
                ],
                [
                    5.998999999999995,
                    -25.10499999999999
                ],
                [
                    6.099000000000004,
                    -25.10499999999999
                ],
                [
                    6.149000000000001,
                    -25.154999999999987
                ],
                [
                    6.649000000000001,
                    -25.154999999999987
                ],
                [
                    6.699000000000012,
                    -25.204999999999984
                ],
                [
                    6.949000000000012,
                    -25.204999999999984
                ],
                [
                    6.998999999999995,
                    -25.154999999999987
                ],
                [
                    7.149000000000001,
                    -25.154999999999987
                ],
                [
                    7.199000000000012,
                    -25.204999999999984
                ],
                [
                    7.449000000000012,
                    -25.204999999999984
                ],
                [
                    7.498999999999995,
                    -25.254999999999995
                ],
                [
                    8.049000000000007,
                    -25.254999999999995
                ],
                [
                    8.099000000000018,
                    -25.304999999999993
                ],
                [
                    8.299000000000007,
                    -25.304999999999993
                ],
                [
                    8.349000000000018,
                    -25.254999999999995
                ],
                [
                    8.498999999999995,
                    -25.254999999999995
                ],
                [
                    8.549000000000007,
                    -25.304999999999993
                ],
                [
                    8.949000000000012,
                    -25.304999999999993
                ],
                [
                    8.998999999999995,
                    -25.35499999999999
                ],
                [
                    9.748999999999995,
                    -25.35499999999999
                ],
                [
                    9.799000000000007,
                    -25.404999999999987
                ],
                [
                    10.59899999999999,
                    -25.404999999999987
                ],
                [
                    10.649000000000001,
                    -25.35499999999999
                ],
                [
                    10.699000000000012,
                    -25.35499999999999
                ],
                [
                    10.84899999999999,
                    -25.204999999999984
                ],
                [
                    10.84899999999999,
                    -25.154999999999987
                ],
                [
                    10.899000000000001,
                    -25.10499999999999
                ],
                [
                    10.899000000000001,
                    -25.054999999999993
                ],
                [
                    10.949000000000012,
                    -25.004999999999995
                ],
                [
                    10.949000000000012,
                    -24.654999999999987
                ],
                [
                    10.998999999999995,
                    -24.60499999999999
                ],
                [
                    10.998999999999995,
                    -23.904999999999987
                ],
                [
                    11.049000000000007,
                    -23.85499999999999
                ],
                [
                    11.049000000000007,
                    -23.154999999999987
                ],
                [
                    11.09899999999999,
                    -23.10499999999999
                ],
                [
                    11.09899999999999,
                    -22.504999999999995
                ],
                [
                    11.049000000000007,
                    -22.454999999999984
                ],
                [
                    11.049000000000007,
                    -22.404999999999987
                ],
                [
                    10.998999999999995,
                    -22.35499999999999
                ],
                [
                    10.998999999999995,
                    -22.304999999999993
                ],
                [
                    10.949000000000012,
                    -22.254999999999995
                ],
                [
                    10.899000000000001,
                    -22.254999999999995
                ],
                [
                    10.84899999999999,
                    -22.204999999999984
                ],
                [
                    10.549000000000007,
                    -22.204999999999984
                ],
                [
                    10.498999999999995,
                    -22.154999999999987
                ],
                [
                    10.449000000000012,
                    -22.204999999999984
                ],
                [
                    10.299000000000007,
                    -22.204999999999984
                ],
                [
                    10.248999999999995,
                    -22.254999999999995
                ],
                [
                    10.149000000000001,
                    -22.254999999999995
                ],
                [
                    10.099000000000018,
                    -22.304999999999993
                ],
                [
                    9.998999999999995,
                    -22.304999999999993
                ],
                [
                    9.799000000000007,
                    -22.504999999999995
                ],
                [
                    9.748999999999995,
                    -22.504999999999995
                ],
                [
                    9.649000000000001,
                    -22.60499999999999
                ],
                [
                    9.498999999999995,
                    -22.60499999999999
                ],
                [
                    9.449000000000012,
                    -22.654999999999987
                ],
                [
                    8.998999999999995,
                    -22.654999999999987
                ],
                [
                    8.949000000000012,
                    -22.60499999999999
                ],
                [
                    8.399000000000001,
                    -22.60499999999999
                ],
                [
                    8.349000000000018,
                    -22.554999999999993
                ],
                [
                    7.748999999999995,
                    -22.554999999999993
                ],
                [
                    7.699000000000012,
                    -22.504999999999995
                ],
                [
                    7.049000000000007,
                    -22.504999999999995
                ],
                [
                    6.998999999999995,
                    -22.454999999999984
                ],
                [
                    6.299000000000007,
                    -22.454999999999984
                ],
                [
                    6.248999999999995,
                    -22.404999999999987
                ],
                [
                    5.549000000000007,
                    -22.404999999999987
                ],
                [
                    5.498999999999995,
                    -22.35499999999999
                ],
                [
                    4.899000000000001,
                    -22.35499999999999
                ],
                [
                    4.849000000000004,
                    -22.304999999999993
                ],
                [
                    4.149000000000001,
                    -22.304999999999993
                ],
                [
                    4.099000000000004,
                    -22.254999999999995
                ],
                [
                    3.399000000000001,
                    -22.254999999999995
                ],
                [
                    3.3490000000000038,
                    -22.204999999999984
                ],
                [
                    2.649000000000001,
                    -22.204999999999984
                ],
                [
                    2.5990000000000038,
                    -22.154999999999987
                ],
                [
                    1.899000000000001,
                    -22.154999999999987
                ],
                [
                    1.8490000000000038,
                    -22.10499999999999
                ],
                [
                    1.149000000000001,
                    -22.10499999999999
                ],
                [
                    1.0990000000000038,
                    -22.054999999999993
                ],
                [
                    0.3990000000000009,
                    -22.054999999999993
                ],
                [
                    0.34900000000000375,
                    -22.004999999999995
                ],
                [
                    -0.3509999999999991,
                    -22.004999999999995
                ],
                [
                    -0.40099999999999625,
                    -21.954999999999984
                ],
                [
                    -1.100999999999999,
                    -21.954999999999984
                ],
                [
                    -1.1509999999999962,
                    -21.904999999999987
                ],
                [
                    -1.850999999999999,
                    -21.904999999999987
                ],
                [
                    -1.9009999999999962,
                    -21.85499999999999
                ],
                [
                    -2.600999999999999,
                    -21.85499999999999
                ],
                [
                    -2.6509999999999962,
                    -21.804999999999993
                ],
                [
                    -3.301000000000002,
                    -21.804999999999993
                ],
                [
                    -3.350999999999999,
                    -21.754999999999995
                ],
                [
                    -4.051000000000002,
                    -21.754999999999995
                ],
                [
                    -4.100999999999999,
                    -21.704999999999984
                ],
                [
                    -4.801000000000002,
                    -21.704999999999984
                ],
                [
                    -4.850999999999999,
                    -21.654999999999987
                ],
                [
                    -5.650999999999996,
                    -21.654999999999987
                ],
                [
                    -5.700999999999993,
                    -21.60499999999999
                ],
                [
                    -6.400999999999996,
                    -21.60499999999999
                ],
                [
                    -6.450999999999993,
                    -21.554999999999993
                ],
                [
                    -7.200999999999993,
                    -21.554999999999993
                ],
                [
                    -7.251000000000005,
                    -21.504999999999995
                ],
                [
                    -8.001000000000005,
                    -21.504999999999995
                ],
                [
                    -8.051000000000002,
                    -21.454999999999984
                ],
                [
                    -8.650999999999996,
                    -21.454999999999984
                ],
                [
                    -8.700999999999993,
                    -21.404999999999987
                ],
                [
                    -9.400999999999996,
                    -21.404999999999987
                ],
                [
                    -9.450999999999993,
                    -21.35499999999999
                ],
                [
                    -10.150999999999996,
                    -21.35499999999999
                ],
                [
                    -10.200999999999993,
                    -21.304999999999993
                ],
                [
                    -11.001000000000005,
                    -21.304999999999993
                ],
                [
                    -11.051000000000002,
                    -21.254999999999995
                ],
                [
                    -11.850999999999999,
                    -21.254999999999995
                ],
                [
                    -11.900999999999996,
                    -21.204999999999984
                ],
                [
                    -12.600999999999999,
                    -21.204999999999984
                ],
                [
                    -12.650999999999996,
                    -21.154999999999987
                ],
                [
                    -13.350999999999999,
                    -21.154999999999987
                ],
                [
                    -13.400999999999996,
                    -21.10499999999999
                ],
                [
                    -14.051000000000002,
                    -21.10499999999999
                ],
                [
                    -14.100999999999999,
                    -21.054999999999993
                ],
                [
                    -14.900999999999996,
                    -21.054999999999993
                ],
                [
                    -14.950999999999993,
                    -21.004999999999995
                ],
                [
                    -15.301000000000002,
                    -21.004999999999995
                ],
                [
                    -15.350999999999999,
                    -20.954999999999984
                ],
                [
                    -15.501000000000005,
                    -20.954999999999984
                ],
                [
                    -15.600999999999999,
                    -20.85499999999999
                ],
                [
                    -15.650999999999996,
                    -20.85499999999999
                ],
                [
                    -15.751000000000005,
                    -20.754999999999995
                ],
                [
                    -15.751000000000005,
                    -20.704999999999984
                ],
                [
                    -15.900999999999996,
                    -20.554999999999993
                ],
                [
                    -15.950999999999993,
                    -20.554999999999993
                ],
                [
                    -16.001000000000005,
                    -20.504999999999995
                ],
                [
                    -16.051000000000002,
                    -20.504999999999995
                ],
                [
                    -16.101,
                    -20.454999999999984
                ],
                [
                    -16.150999999999996,
                    -20.454999999999984
                ],
                [
                    -16.200999999999993,
                    -20.404999999999987
                ],
                [
                    -16.301000000000002,
                    -20.404999999999987
                ],
                [
                    -16.351,
                    -20.35499999999999
                ],
                [
                    -16.650999999999996,
                    -20.35499999999999
                ],
                [
                    -16.700999999999993,
                    -20.304999999999993
                ],
                [
                    -16.900999999999996,
                    -20.304999999999993
                ],
                [
                    -16.950999999999993,
                    -20.35499999999999
                ],
                [
                    -17.301000000000002,
                    -20.35499999999999
                ],
                [
                    -17.351,
                    -20.404999999999987
                ],
                [
                    -17.501000000000005,
                    -20.404999999999987
                ],
                [
                    -17.551000000000002,
                    -20.454999999999984
                ],
                [
                    -17.700999999999993,
                    -20.454999999999984
                ],
                [
                    -17.751000000000005,
                    -20.504999999999995
                ],
                [
                    -17.851,
                    -20.504999999999995
                ],
                [
                    -17.900999999999996,
                    -20.554999999999993
                ],
                [
                    -17.950999999999993,
                    -20.554999999999993
                ],
                [
                    -18.051000000000002,
                    -20.654999999999987
                ],
                [
                    -18.200999999999993,
                    -20.654999999999987
                ],
                [
                    -18.251000000000005,
                    -20.704999999999984
                ],
                [
                    -18.400999999999996,
                    -20.704999999999984
                ],
                [
                    -18.450999999999993,
                    -20.654999999999987
                ],
                [
                    -18.601,
                    -20.654999999999987
                ],
                [
                    -18.650999999999996,
                    -20.60499999999999
                ],
                [
                    -18.700999999999993,
                    -20.60499999999999
                ],
                [
                    -18.801000000000002,
                    -20.504999999999995
                ],
                [
                    -18.851,
                    -20.504999999999995
                ],
                [
                    -19.051000000000002,
                    -20.304999999999993
                ],
                [
                    -19.101,
                    -20.304999999999993
                ],
                [
                    -19.150999999999996,
                    -20.254999999999995
                ],
                [
                    -19.200999999999993,
                    -20.254999999999995
                ],
                [
                    -19.251000000000005,
                    -20.204999999999984
                ],
                [
                    -19.351,
                    -20.204999999999984
                ],
                [
                    -19.400999999999996,
                    -20.154999999999987
                ],
                [
                    -19.450999999999993,
                    -20.154999999999987
                ],
                [
                    -19.501000000000005,
                    -20.10499999999999
                ],
                [
                    -19.700999999999993,
                    -20.10499999999999
                ],
                [
                    -19.751000000000005,
                    -20.054999999999993
                ],
                [
                    -20.200999999999993,
                    -20.054999999999993
                ]
            ]
        }
    ]
}